sec_visualizers/__init__.py
sec_visualizers/helper.py
sec_visualizers/visualizer.py
sec_visualizers/templates/index.html
sec_visualizers-0.9.dist-info/METADATA
sec_visualizers-0.9.dist-info/WHEEL
sec_visualizers-0.9.dist-info/top_level.txt
sec_visualizers-0.9.dist-info/RECORD
