Metadata-Version: 2.1
Name: sec-visualizers
Version: 0.9
Summary: A package to visualize SEC filings
Home-page: https://github.com/john-friedman/SEC-Visualizers
Author: John Friedman
Requires-Dist: flask
